MANIFEST.in
README.md
pyproject.toml
setup.py
mat_neuron/__init__.py
mat_neuron/_pymodel.py
mat_neuron/_version.py
mat_neuron/core.py
mat_neuron.egg-info/PKG-INFO
mat_neuron.egg-info/SOURCES.txt
mat_neuron.egg-info/dependency_links.txt
mat_neuron.egg-info/requires.txt
mat_neuron.egg-info/top_level.txt
src/model.cpp
test/test_model.py