Metadata-Version: 2.1
Name: mat-neuron
Version: 0.4.3
Summary: Python code to integrate and evaluate likelihood for MAT neuron model
Home-page: UNKNOWN
Author: Tyler Robbins
Maintainer: C Daniel Meliza
License: UNKNOWN
Platform: UNKNOWN
Classifier: Development Status :: 3 - Alpha
Classifier: Intended Audience :: Science/Research
Classifier: License :: OSI Approved :: GNU General Public License (GPL)
Classifier: Programming Language :: Python
Classifier: Topic :: Scientific/Engineering
Classifier: Topic :: Internet :: WWW/HTTP
Classifier: Topic :: Internet :: WWW/HTTP :: Dynamic Content
